MANIFEST.in
authors.txt
license.txt
pypi_upload.txt
setup.py
databases/burcat_thr.xml
databases/nasa9polynomials.xml
test/__init__.py
test/test_burcat.py
test/test_iapws.py
test/test_units.py
thermopy/__init__.py
thermopy/burcat.py
thermopy/constants.py
thermopy/iapws.py
thermopy/nasa9polynomials.py
thermopy/units.py
thermopy2.egg-info/PKG-INFO
thermopy2.egg-info/SOURCES.txt
thermopy2.egg-info/dependency_links.txt
thermopy2.egg-info/not-zip-safe
thermopy2.egg-info/requires.txt
thermopy2.egg-info/top_level.txt